python_packaging_swc_zm/__init__.py
python_packaging_swc_zm/math.py
python_packaging_swc_zm-0.0.0.dist-info/LICENSE.yaml
python_packaging_swc_zm-0.0.0.dist-info/METADATA
python_packaging_swc_zm-0.0.0.dist-info/WHEEL
python_packaging_swc_zm-0.0.0.dist-info/top_level.txt
python_packaging_swc_zm-0.0.0.dist-info/RECORD
